kamiwaza-0.5.0.dist-info/licenses/LICENSE
kamiwaza_client/__init__.py
kamiwaza_client/authentication.py
kamiwaza_client/client.py
kamiwaza_client/config.py
kamiwaza_client/exceptions.py
kamiwaza_client/utils.py
kamiwaza_client/schemas/__init__.py
kamiwaza_client/schemas/activity.py
kamiwaza_client/schemas/apps.py
kamiwaza_client/schemas/auth.py
kamiwaza_client/schemas/catalog.py
kamiwaza_client/schemas/cluster.py
kamiwaza_client/schemas/embedding.py
kamiwaza_client/schemas/lab.py
kamiwaza_client/schemas/prompts.py
kamiwaza_client/schemas/retrieval.py
kamiwaza_client/schemas/tools.py
kamiwaza_client/schemas/vectordb.py
kamiwaza_client/schemas/models/__init__.py
kamiwaza_client/schemas/models/downloads.py
kamiwaza_client/schemas/models/model.py
kamiwaza_client/schemas/models/model_family.py
kamiwaza_client/schemas/models/model_file.py
kamiwaza_client/schemas/models/model_search.py
kamiwaza_client/schemas/serving/__init__.py
kamiwaza_client/schemas/serving/inference.py
kamiwaza_client/schemas/serving/prompt_format.py
kamiwaza_client/schemas/serving/serving.py
kamiwaza_client/services/__init__.py
kamiwaza_client/services/activity.py
kamiwaza_client/services/apps.py
kamiwaza_client/services/auth.py
kamiwaza_client/services/base_service.py
kamiwaza_client/services/catalog.py
kamiwaza_client/services/cluster.py
kamiwaza_client/services/embedding.py
kamiwaza_client/services/lab.py
kamiwaza_client/services/openai.py
kamiwaza_client/services/prompts.py
kamiwaza_client/services/retrieval.py
kamiwaza_client/services/serving.py
kamiwaza_client/services/tools.py
kamiwaza_client/services/vectordb.py
kamiwaza_client/services/models/__init__.py
kamiwaza_client/services/models/base.py
kamiwaza_client/services/models/compatibility.py
kamiwaza_client/services/models/configs.py
kamiwaza_client/services/models/downloads.py
kamiwaza_client/services/models/files.py
kamiwaza_client/services/models/search.py
kamiwaza_client/utils/__init__.py
kamiwaza_client/utils/download_tracker.py
kamiwaza_client/utils/progress_formatter.py
kamiwaza-0.5.0.dist-info/METADATA
kamiwaza-0.5.0.dist-info/WHEEL
kamiwaza-0.5.0.dist-info/top_level.txt
kamiwaza-0.5.0.dist-info/RECORD
