Metadata-Version: 2.4
Name: kamiwaza
Version: 0.5.0
Summary: Python client library for the Kamiwaza AI Platform
Home-page: https://github.com/kamiwaza/kamiwaza-client
Author: Kamiwaza Team
Author-email: tyler@kamiwaza.ai
Classifier: Development Status :: 4 - Beta
Classifier: Intended Audience :: Developers
Classifier: License :: OSI Approved :: MIT License
Classifier: Operating System :: OS Independent
Classifier: Programming Language :: Python :: 3
Classifier: Programming Language :: Python :: 3.10
Classifier: Programming Language :: Python :: 3.11
Classifier: Topic :: Software Development :: Libraries :: Python Modules
Classifier: Topic :: Scientific/Engineering :: Artificial Intelligence
Requires-Python: >=3.10
License-File: LICENSE
Requires-Dist: requests
Requires-Dist: pydantic[email]
Requires-Dist: httpx
Requires-Dist: openai>=1.0
Dynamic: author
Dynamic: author-email
Dynamic: classifier
Dynamic: description
Dynamic: description-content-type
Dynamic: home-page
Dynamic: license-file
Dynamic: requires-dist
Dynamic: requires-python
Dynamic: summary
